qsiprep_docker.py
qsiprep_singularity.py
python3.8/site-packages/_virtualenv.pth
python3.8/site-packages/_virtualenv.py
python3.8/site-packages/distutils-precedence.pth
python3.8/site-packages/setuptools-57.0.0.virtualenv
python3.8/site-packages/wheel-0.36.2.virtualenv
python3.8/site-packages/__pycache__/_virtualenv.cpython-38.pyc
python3.8/site-packages/_distutils_hack/__init__.py
python3.8/site-packages/_distutils_hack/override.py
python3.8/site-packages/_distutils_hack/__pycache__/__init__.cpython-38.pyc
python3.8/site-packages/_distutils_hack/__pycache__/override.cpython-38.pyc
python3.8/site-packages/pip/__init__.py
python3.8/site-packages/pip/__main__.py
python3.8/site-packages/pip/__pip-runner__.py
python3.8/site-packages/pip/py.typed
python3.8/site-packages/pip/__pycache__/__init__.cpython-38.pyc
python3.8/site-packages/pip/__pycache__/__main__.cpython-38.pyc
python3.8/site-packages/pip/__pycache__/__pip-runner__.cpython-38.pyc
python3.8/site-packages/pip/_internal/__init__.py
python3.8/site-packages/pip/_internal/build_env.py
python3.8/site-packages/pip/_internal/cache.py
python3.8/site-packages/pip/_internal/configuration.py
python3.8/site-packages/pip/_internal/exceptions.py
python3.8/site-packages/pip/_internal/main.py
python3.8/site-packages/pip/_internal/pyproject.py
python3.8/site-packages/pip/_internal/self_outdated_check.py
python3.8/site-packages/pip/_internal/wheel_builder.py
python3.8/site-packages/pip/_internal/__pycache__/__init__.cpython-38.pyc
python3.8/site-packages/pip/_internal/__pycache__/build_env.cpython-38.pyc
python3.8/site-packages/pip/_internal/__pycache__/cache.cpython-38.pyc
python3.8/site-packages/pip/_internal/__pycache__/configuration.cpython-38.pyc
python3.8/site-packages/pip/_internal/__pycache__/exceptions.cpython-38.pyc
python3.8/site-packages/pip/_internal/__pycache__/main.cpython-38.pyc
python3.8/site-packages/pip/_internal/__pycache__/pyproject.cpython-38.pyc
python3.8/site-packages/pip-23.2.1.dist-info/AUTHORS.txt
python3.8/site-packages/pip-23.2.1.dist-info/INSTALLER
python3.8/site-packages/pip-23.2.1.dist-info/LICENSE.txt
python3.8/site-packages/pip-23.2.1.dist-info/METADATA
python3.8/site-packages/pip-23.2.1.dist-info/RECORD
python3.8/site-packages/pip-23.2.1.dist-info/REQUESTED
python3.8/site-packages/pip-23.2.1.dist-info/WHEEL
python3.8/site-packages/pip-23.2.1.dist-info/entry_points.txt
python3.8/site-packages/pip-23.2.1.dist-info/top_level.txt
python3.8/site-packages/setuptools-57.0.0.dist-info/INSTALLER
python3.8/site-packages/setuptools-57.0.0.dist-info/LICENSE
python3.8/site-packages/setuptools-57.0.0.dist-info/METADATA
python3.8/site-packages/setuptools-57.0.0.dist-info/RECORD
python3.8/site-packages/setuptools-57.0.0.dist-info/WHEEL
python3.8/site-packages/setuptools-57.0.0.dist-info/dependency_links.txt
python3.8/site-packages/setuptools-57.0.0.dist-info/entry_points.txt
python3.8/site-packages/setuptools-57.0.0.dist-info/top_level.txt
python3.8/site-packages/wheel-0.36.2.dist-info/INSTALLER
python3.8/site-packages/wheel-0.36.2.dist-info/LICENSE.txt
python3.8/site-packages/wheel-0.36.2.dist-info/METADATA
python3.8/site-packages/wheel-0.36.2.dist-info/RECORD
python3.8/site-packages/wheel-0.36.2.dist-info/WHEEL
python3.8/site-packages/wheel-0.36.2.dist-info/entry_points.txt
python3.8/site-packages/wheel-0.36.2.dist-info/top_level.txt
qsiprep_container-0.19.1.dist-info/METADATA
qsiprep_container-0.19.1.dist-info/WHEEL
qsiprep_container-0.19.1.dist-info/entry_points.txt
qsiprep_container-0.19.1.dist-info/top_level.txt
qsiprep_container-0.19.1.dist-info/RECORD
