Metadata-Version: 2.1
Name: qsiprep-container
Version: 0.19.1
Summary: qsiprep is a non-DTI diffusion-weighted image pre-processing pipeline that is designed to provide an easily accessible, state-of-the-art interface that is robust to differences in scan acquisition protocols and that requires minimal user input, while providing easily interpretable and comprehensive error and output reporting.
Home-page: https://github.com/pennbbl/qsiprep
Author: 
Author-email: 
Maintainer: 
Maintainer-email: 
License: 3-clause BSD
Platform: UNKNOWN
Classifier: Development Status :: 3 - Alpha
Classifier: Intended Audience :: Science/Research
Classifier: License :: OSI Approved :: BSD License
Classifier: Programming Language :: Python :: 3.6
